{
  "swagger": "2.0",
  "info": {
    "title": "api.proto",
    "version": "version not set"
  },
  "tags": [
    {
      "name": "Admin"
    }
  ],
  "consumes": [
    "application/json"
  ],
  "produces": [
    "application/json"
  ],
  "paths": {
    "/v1/movie": {
      "post": {
        "operationId": "Admin_MovieCreate",
        "responses": {
          "200": {
            "description": "A successful response.",
            "schema": {
              "$ref": "#/definitions/apiMovieCreateResponse"
            }
          },
          "default": {
            "description": "An unexpected error response.",
            "schema": {
              "$ref": "#/definitions/rpcStatus"
            }
          }
        },
        "parameters": [
          {
            "name": "body",
            "in": "body",
            "required": true,
            "schema": {
              "$ref": "#/definitions/apiMovieCreateRequest"
            }
          }
        ],
        "tags": [
          "Admin"
        ]
      }
    },
    "/v1/movie/update": {
      "post": {
        "operationId": "Admin_MovieUpdate",
        "responses": {
          "200": {
            "description": "A successful response.",
            "schema": {
              "$ref": "#/definitions/apiMovieUpdateResponse"
            }
          },
          "default": {
            "description": "An unexpected error response.",
            "schema": {
              "$ref": "#/definitions/rpcStatus"
            }
          }
        },
        "parameters": [
          {
            "name": "body",
            "in": "body",
            "required": true,
            "schema": {
              "$ref": "#/definitions/apiMovieUpdateRequest"
            }
          }
        ],
        "tags": [
          "Admin"
        ]
      }
    },
    "/v1/movie/{id}": {
      "delete": {
        "operationId": "Admin_MovieDelete",
        "responses": {
          "200": {
            "description": "A successful response.",
            "schema": {
              "$ref": "#/definitions/apiMovieDeleteResponse"
            }
          },
          "default": {
            "description": "An unexpected error response.",
            "schema": {
              "$ref": "#/definitions/rpcStatus"
            }
          }
        },
        "parameters": [
          {
            "name": "id",
            "in": "path",
            "required": true,
            "type": "string",
            "format": "uint64"
          }
        ],
        "tags": [
          "Admin"
        ]
      }
    },
    "/v1/movies": {
      "get": {
        "operationId": "Admin_MovieList",
        "responses": {
          "200": {
            "description": "A successful response.",
            "schema": {
              "$ref": "#/definitions/apiMovieListResponse"
            }
          },
          "default": {
            "description": "An unexpected error response.",
            "schema": {
              "$ref": "#/definitions/rpcStatus"
            }
          }
        },
        "tags": [
          "Admin"
        ]
      }
    }
  },
  "definitions": {
    "apiMovie": {
      "type": "object",
      "properties": {
        "id": {
          "type": "string",
          "format": "uint64"
        },
        "title": {
          "type": "string"
        },
        "year": {
          "type": "integer",
          "format": "int32"
        }
      }
    },
    "apiMovieCreateRequest": {
      "type": "object",
      "properties": {
        "title": {
          "type": "string"
        },
        "year": {
          "type": "integer",
          "format": "int32"
        }
      }
    },
    "apiMovieCreateResponse": {
      "type": "object"
    },
    "apiMovieDeleteResponse": {
      "type": "object"
    },
    "apiMovieListResponse": {
      "type": "object",
      "properties": {
        "movie": {
          "type": "array",
          "items": {
            "$ref": "#/definitions/apiMovie"
          }
        }
      }
    },
    "apiMovieUpdateRequest": {
      "type": "object",
      "properties": {
        "movie": {
          "$ref": "#/definitions/apiMovie"
        }
      }
    },
    "apiMovieUpdateResponse": {
      "type": "object"
    },
    "protobufAny": {
      "type": "object",
      "properties": {
        "@type": {
          "type": "string"
        }
      },
      "additionalProperties": {}
    },
    "rpcStatus": {
      "type": "object",
      "properties": {
        "code": {
          "type": "integer",
          "format": "int32"
        },
        "message": {
          "type": "string"
        },
        "details": {
          "type": "array",
          "items": {
            "$ref": "#/definitions/protobufAny"
          }
        }
      }
    }
  }
}
